{
  "indexes": [
    {
      "collectionGroup": "printJobs",
      "queryScope": "COLLECTION",
      "fields": [
        { "fieldPath": "uid", "order": "ASCENDING" },
        { "fieldPath": "timestamp", "order": "DESCENDING" }
      ]
    },
    {
      "collectionGroup": "printJobs",
      "queryScope": "COLLECTION",
      "fields": [
        { "fieldPath": "uid", "order": "ASCENDING" },
        { "fieldPath": "createdAt", "order": "DESCENDING" }
      ]
    },
    {
      "collectionGroup": "laminationJobs",
      "queryScope": "COLLECTION",
      "fields": [
        { "fieldPath": "uid", "order": "ASCENDING" },
        { "fieldPath": "timestamp", "order": "DESCENDING" }
      ]
    },
    {
      "collectionGroup": "laminationJobs",
      "queryScope": "COLLECTION",
      "fields": [
        { "fieldPath": "uid", "order": "ASCENDING" },
        { "fieldPath": "createdAt", "order": "DESCENDING" }
      ]
    },
    {
      "collectionGroup": "income",
      "queryScope": "COLLECTION",
      "fields": [
        { "fieldPath": "uid", "order": "ASCENDING" },
        { "fieldPath": "createdAt", "order": "DESCENDING" }
      ]
    }
  ],
  "fieldOverrides": []
}

